odoo9_addon_account_operating_unit-9.0.1.0.0.99.dev31-py2.7-nspkg.pth
odoo9_addon_account_operating_unit-9.0.1.0.0.99.dev31.dist-info/DESCRIPTION.rst
odoo9_addon_account_operating_unit-9.0.1.0.0.99.dev31.dist-info/METADATA
odoo9_addon_account_operating_unit-9.0.1.0.0.99.dev31.dist-info/RECORD
odoo9_addon_account_operating_unit-9.0.1.0.0.99.dev31.dist-info/WHEEL
odoo9_addon_account_operating_unit-9.0.1.0.0.99.dev31.dist-info/metadata.json
odoo9_addon_account_operating_unit-9.0.1.0.0.99.dev31.dist-info/namespace_packages.txt
odoo9_addon_account_operating_unit-9.0.1.0.0.99.dev31.dist-info/top_level.txt
odoo_addons/account_operating_unit/README.rst
odoo_addons/account_operating_unit/__init__.py
odoo_addons/account_operating_unit/__openerp__.py
odoo_addons/account_operating_unit/models/__init__.py
odoo_addons/account_operating_unit/models/account_journal.py
odoo_addons/account_operating_unit/models/account_move.py
odoo_addons/account_operating_unit/models/account_payment.py
odoo_addons/account_operating_unit/models/company.py
odoo_addons/account_operating_unit/models/invoice.py
odoo_addons/account_operating_unit/report/__init__.py
odoo_addons/account_operating_unit/report/account_invoice_report.py
odoo_addons/account_operating_unit/security/account_security.xml
odoo_addons/account_operating_unit/static/description/icon.png
odoo_addons/account_operating_unit/tests/__init__.py
odoo_addons/account_operating_unit/tests/test_account_operating_unit.py
odoo_addons/account_operating_unit/tests/test_cross_ou_journal_entry.py
odoo_addons/account_operating_unit/tests/test_invoice_operating_unit.py
odoo_addons/account_operating_unit/tests/test_operating_unit_security.py
odoo_addons/account_operating_unit/tests/test_payment_operating_unit.py
odoo_addons/account_operating_unit/views/account_invoice_report_view.xml
odoo_addons/account_operating_unit/views/account_journal_view.xml
odoo_addons/account_operating_unit/views/account_move_view.xml
odoo_addons/account_operating_unit/views/account_payment_view.xml
odoo_addons/account_operating_unit/views/company_view.xml
odoo_addons/account_operating_unit/views/invoice_view.xml
odoo_addons/account_operating_unit/views/report_agedpartnerbalance.xml
odoo_addons/account_operating_unit/views/report_financial.xml
odoo_addons/account_operating_unit/views/report_trialbalance.xml
odoo_addons/account_operating_unit/wizard/__init__.py
odoo_addons/account_operating_unit/wizard/account_financial_report.py
